{
  "entrypoints": [
    "main"
  ],
  "origins": {
    "237": [
      237
    ],
    "17896441": [
      869,
      401
    ],
    "main": [
      354,
      869,
      792
    ],
    "runtime~main": [
      792,
      869,
      354
    ],
    "0480b142": [
      70
    ],
    "0e384e19": [
      976
    ],
    "22dd74f7": [
      567
    ],
    "280d6575": [
      190
    ],
    "5759393e": [
      109
    ],
    "5e95c892": [
      647
    ],
    "723bacd8": [
      211
    ],
    "72e14192": [
      814
    ],
    "7f3d0e17": [
      428
    ],
    "9278c823": [
      7
    ],
    "a30d1f92": [
      419
    ],
    "a7bd4aaa": [
      98
    ],
    "a94703ab": [
      869,
      48
    ],
    "aba21aa0": [
      742
    ],
    "d4ae24d8": [
      547
    ],
    "d589d3a7": [
      924
    ],
    "dec09136": [
      718
    ],
    "e3098f48": [
      168
    ],
    "e376fc56": [
      480
    ],
    "edefc60b": [
      624
    ],
    "styles": [
      48,
      354,
      401,
      792,
      869
    ]
  },
  "assets": {
    "7": {
      "js": [
        {
          "file": "assets/js/9278c823.290969e5.js",
          "hash": "afb7ac81d42c2875",
          "publicPath": "/assets/js/9278c823.290969e5.js"
        }
      ]
    },
    "48": {
      "js": [
        {
          "file": "assets/js/a94703ab.cb2ca397.js",
          "hash": "bfe0842bf863a240",
          "publicPath": "/assets/js/a94703ab.cb2ca397.js"
        }
      ]
    },
    "70": {
      "js": [
        {
          "file": "assets/js/0480b142.3e9bad33.js",
          "hash": "8d8c6e1e43ed7002",
          "publicPath": "/assets/js/0480b142.3e9bad33.js"
        }
      ]
    },
    "98": {
      "js": [
        {
          "file": "assets/js/a7bd4aaa.eafd4039.js",
          "hash": "b0c3f3d67fe1e196",
          "publicPath": "/assets/js/a7bd4aaa.eafd4039.js"
        }
      ]
    },
    "109": {
      "js": [
        {
          "file": "assets/js/5759393e.2475d8d6.js",
          "hash": "05fb9be5bf0d055d",
          "publicPath": "/assets/js/5759393e.2475d8d6.js"
        }
      ]
    },
    "168": {
      "js": [
        {
          "file": "assets/js/e3098f48.86b6cff6.js",
          "hash": "f4fc24ba92d607b9",
          "publicPath": "/assets/js/e3098f48.86b6cff6.js"
        }
      ]
    },
    "190": {
      "js": [
        {
          "file": "assets/js/280d6575.a0e88d4a.js",
          "hash": "be690ffbde093e31",
          "publicPath": "/assets/js/280d6575.a0e88d4a.js"
        }
      ]
    },
    "211": {
      "js": [
        {
          "file": "assets/js/723bacd8.8a0dd792.js",
          "hash": "f75aca7ae49a7fb3",
          "publicPath": "/assets/js/723bacd8.8a0dd792.js"
        }
      ]
    },
    "237": {
      "js": [
        {
          "file": "assets/js/237.3b7b972a.js",
          "hash": "7d04adf6b9f37968",
          "publicPath": "/assets/js/237.3b7b972a.js"
        }
      ]
    },
    "354": {
      "js": [
        {
          "file": "assets/js/runtime~main.ed905750.js",
          "hash": "ac4e155512d39995",
          "publicPath": "/assets/js/runtime~main.ed905750.js"
        }
      ]
    },
    "401": {
      "js": [
        {
          "file": "assets/js/17896441.e4ac8fe3.js",
          "hash": "1a3ae4362f2191ce",
          "publicPath": "/assets/js/17896441.e4ac8fe3.js"
        }
      ]
    },
    "419": {
      "js": [
        {
          "file": "assets/js/a30d1f92.1c6b87eb.js",
          "hash": "fb2908581ee569f1",
          "publicPath": "/assets/js/a30d1f92.1c6b87eb.js"
        }
      ]
    },
    "428": {
      "js": [
        {
          "file": "assets/js/7f3d0e17.fb6a0375.js",
          "hash": "7add03afd7513449",
          "publicPath": "/assets/js/7f3d0e17.fb6a0375.js"
        }
      ]
    },
    "480": {
      "js": [
        {
          "file": "assets/js/e376fc56.7af182a2.js",
          "hash": "c3f1fd102aea6d4f",
          "publicPath": "/assets/js/e376fc56.7af182a2.js"
        }
      ]
    },
    "547": {
      "js": [
        {
          "file": "assets/js/d4ae24d8.2c2f73a0.js",
          "hash": "e04ecb8f1d6fb677",
          "publicPath": "/assets/js/d4ae24d8.2c2f73a0.js"
        }
      ]
    },
    "567": {
      "js": [
        {
          "file": "assets/js/22dd74f7.c561e224.js",
          "hash": "f574436e9faf01e9",
          "publicPath": "/assets/js/22dd74f7.c561e224.js"
        }
      ]
    },
    "624": {
      "js": [
        {
          "file": "assets/js/edefc60b.c9dc9727.js",
          "hash": "5a321b0c286f38b8",
          "publicPath": "/assets/js/edefc60b.c9dc9727.js"
        }
      ]
    },
    "647": {
      "js": [
        {
          "file": "assets/js/5e95c892.e5bd47bf.js",
          "hash": "405c120d54f3ce7d",
          "publicPath": "/assets/js/5e95c892.e5bd47bf.js"
        }
      ]
    },
    "718": {
      "js": [
        {
          "file": "assets/js/dec09136.74e9e4d4.js",
          "hash": "163b4b6ae9c2a3ac",
          "publicPath": "/assets/js/dec09136.74e9e4d4.js"
        }
      ]
    },
    "742": {
      "js": [
        {
          "file": "assets/js/aba21aa0.706c5da8.js",
          "hash": "f407448bf557864f",
          "publicPath": "/assets/js/aba21aa0.706c5da8.js"
        }
      ]
    },
    "792": {
      "js": [
        {
          "file": "assets/js/main.41b9b3f1.js",
          "hash": "0540c1a9498abda0",
          "publicPath": "/assets/js/main.41b9b3f1.js"
        }
      ]
    },
    "814": {
      "js": [
        {
          "file": "assets/js/72e14192.f1aedfd2.js",
          "hash": "2e7f2a42aebd475e",
          "publicPath": "/assets/js/72e14192.f1aedfd2.js"
        }
      ]
    },
    "869": {
      "css": [
        {
          "file": "assets/css/styles.ca104b92.css",
          "hash": "40a59a0ea49fdceb",
          "publicPath": "/assets/css/styles.ca104b92.css"
        }
      ]
    },
    "924": {
      "js": [
        {
          "file": "assets/js/d589d3a7.e97cbdef.js",
          "hash": "0d290d2e4ec916f2",
          "publicPath": "/assets/js/d589d3a7.e97cbdef.js"
        }
      ]
    },
    "976": {
      "js": [
        {
          "file": "assets/js/0e384e19.4d714c76.js",
          "hash": "9dfe9b1ddb346d51",
          "publicPath": "/assets/js/0e384e19.4d714c76.js"
        }
      ]
    }
  }
}